{"code": "10330", "level": "本科", "name": "南京体育学院", "phys": [{"universityId": 630, "universityCode": "10330", "universityMajorGroup": "201", "planCount": 6, "chong": 0, "wen": 0, "bao": 0, "yi": 1, "nan": 0, "none": 0, "enrollProbability": 96, "universityRule": "YI", "type": "ACADEMY_GROUP", "histories": [{"recruitCount": 4, "minScore": 507, "score": 516, "minPlace": 132499, "batchLine": 439, "year": 2023}, {"recruitCount": 6, "minScore": 508, "score": 518, "minPlace": 134290, "batchLine": 442, "year": 2024}, {"recruitCount": 6, "minScore": 517, "score": 522, "minPlace": 135039, "batchLine": 436, "year": 2025}], "branches": [{"id": null, "enrollYear": 2025, "minScore": 517, "minPlace": 135039, "universityCode": "10330", "branchScore": "[{\"2025\":\"517,135039,6\"},{\"2024\":\"508,134290,6\"},{\"2023\":\"507,132499,4\"}]", "schoolScore": "[{\"2025\":\"517,135039,6\"},{\"2024\":\"508,134290,6\"},{\"2023\":\"507,132499,4\"}]", "majorParityScore": "[{\"2025\":522},{\"2024\":518},{\"2023\":516}]", "schoolParityScore": "[{\"2025\":\"522\"},{\"2024\":\"518\"},{\"2023\":\"516\"}]", "majorCode": "001", "majorName": "康复治疗学", "majorRemarks": "（办学地点：灵谷寺校区）", "branchPlanNum": 6, "schoolPlanNum": 6, "claim": "化", "schoolLowestScore": null, "branchLowestScore": null, "studyYear": "4", "studyCost": "6800", "universityMajorGroup": "201", "enrollProbability": null, "universityRule": "YI", "zsgkId": 182, "categoryName": "体育", "batch": "本科批", "checkClaim": false, "enrollNum": null, "enrolmentRate": "8.00", "historyPlanNum": null, "historyScore": null, "level": "本科", "logo": "https://static-file.daxue.cn/images/南京体育学院.png", "nextClaim": null, "nextYear": 2026, "propertyName": "公办", "province": "江苏", "recruitCode": "10330", "tags": "保研资格", "tag": "色盲,色弱", "majorLevel": null, "specialPlan": false, "undergraduateLevel": null, "universityId": 630, "checkPredict": false}], "checkPredict": false}], "hist": []}